{
"type": "FeatureCollection",
"name": "benqueViejo",
"crs": { "type": "name", "properties": { "name": "urn:ogc:def:crs:OGC:1.3:CRS84" } },
"features": [
{ "type": "Feature", "properties": { "SETTNAME": "Benque Viejo", "DISTRICT": "Cayo", "TYPE": "Town", "POPULATION": 6163.0, "X_COORD": 272293.59375, "Y_COORD": 1888898.0 }, "geometry": { "type": "Point", "coordinates": [ -89.13961, 17.075 ] } }
]
}
