{
"type": "FeatureCollection",
"name": "lowerBartonCreek",
"crs": { "type": "name", "properties": { "name": "urn:ogc:def:crs:OGC:1.3:CRS84" } },
"features": [
{ "type": "Feature", "properties": { "SETTNAME": "Lower Barton Creek", "DISTRICT": "Cayo", "TYPE": "Community", "POPULATION": 380.0, "X_COORD": 294468.19918, "Y_COORD": 1896932.38809 }, "geometry": { "type": "Point", "coordinates": [ -88.93208, 17.14968 ] } }
]
}
